Products.DateRecurringIndex-3.0.0-py2.7-nspkg.pth
Products/DateRecurringIndex/__init__.py
Products/DateRecurringIndex/index.py
Products/DateRecurringIndex/testing.py
Products/DateRecurringIndex/tests.py
Products/DateRecurringIndex/www/addDRIndex.dtml
Products/DateRecurringIndex/www/browseIndex.dtml
Products/DateRecurringIndex/www/index.gif
Products/DateRecurringIndex/www/manageDRIndex.zpt
Products.DateRecurringIndex-3.0.0.dist-info/METADATA
Products.DateRecurringIndex-3.0.0.dist-info/RECORD
Products.DateRecurringIndex-3.0.0.dist-info/WHEEL
Products.DateRecurringIndex-3.0.0.dist-info/namespace_packages.txt
Products.DateRecurringIndex-3.0.0.dist-info/top_level.txt
