Metadata-Version: 2.1
Name: Products.DateRecurringIndex
Version: 3.0.0
Summary: Zope 2 date index with support for recurring events.
Home-page: https://github.com/collective/Products.DateRecurringIndex
Author: BlueDynamics Alliance
Author-email: dev@bluedynamics.com
License: BSD
Keywords: zope zope2 index catalog date recurring
Platform: UNKNOWN
Classifier: Development Status :: 5 - Production/Stable
Classifier: Environment :: Web Environment
Classifier: Framework :: Zope2
Classifier: License :: OSI Approved :: BSD License
Classifier: Operating System :: OS Independent
Classifier: Programming Language :: Python
Classifier: Programming Language :: Python :: 2.7
Classifier: Programming Language :: Python :: 3.6
Classifier: Topic :: Internet :: WWW/HTTP :: Dynamic Content
Provides-Extra: test
Requires-Dist: setuptools
Requires-Dist: BTrees
Requires-Dist: plone.event
Requires-Dist: Products.ZCatalog
Requires-Dist: ZODB
Requires-Dist: zope.interface
Requires-Dist: zope.schema
Provides-Extra: test
Requires-Dist: pytz; extra == 'test'
Requires-Dist: plone.testing; extra == 'test'
